Workbook

Sheet LEEME
B2: MODELO SIRD — ARGENTINA COVID-19
B3: Insumo para el PCR de AR-L1326 (Respuesta a la Emergencia de Salud Publica COVID-19)
B5: QUE HACE ESTE LIBRO
B6: Integra un modelo compartimental SIRD (Susceptible-Infeccioso-Recuperado-Fallecido) sobre
B7: paso semanal, calibrado contra la mortalidad observada en Argentina entre marzo 2020 y junio 2022.
B8: Todas las celdas de calculo son formulas vivas: al cambiar un parametro, el modelo recalcula.
B10: QUE NO HACE
B11: NO estima el efecto causal del prestamo BID sobre la epidemia. El beta(t) calibrado captura
B12: TODAS las intervenciones simultaneas (ASPO, fronteras, vacunacion con fondos propios, COVAX,
B13: otros prestamos multilaterales, capacidad preexistente). Atribuir la trayectoria completa al
B14: prestamo seria incorrecto y OVE lo observaria.
B16: El uso legitimo para la seccion de EFECTIVIDAD es el canal de deteccion del Componente 2:
... B44: confirmados son funcion de la capacidad de testeo tanto como de la incidencia real.

Sheet Parametros
B2: PARAMETROS DEL MODELO
B4: Parametro | C4: Valor | D4: Min | E4: Max | F4: Unidad | G4: Fuente / Justificacion
B5: DEMOGRAFIA Y CONDICIONES INICIALES
B6: Poblacion Argentina (N) | C6: 45510324 | F6: personas | G6: OWID / INDEC 2020. Serie 'population'.
B7: Fraccion susceptible inicial (S0/N) | C7: 1 | D7: 0.9 | E7: 1 | F7: fraccion | G7: Se adopta 1.00. El analisis ex ante y Borracchi&Giglio asumen 0.90 ('10% con inmunidad natural'); ese supuesto no tiene respaldo empirico y la evidencia serologica posterior lo contradice.
B8: Infecciosos iniciales (I0) | C8: 100 | D8: 10 | E8: 500 | F8: personas | G8: Semilla al 08-mar-2020. El analisis ex ante usa 1 caso; con paso semanal y subregistro inicial, 100 es mas plausible.
B10: PARAMETROS BIOLOGICOS (SE FIJAN, NO SE ESTIMAN)
B11: Con series agregadas no es posible identificar simultaneamente beta, gamma e IFR: distintas combinaciones producen curvas casi identicas.
B12: Duracion del periodo infeccioso (D) | C12: 10 | D12: 7 | E12: 14 | F12: dias | G12: Consenso post-pandemia. NOTA: el analisis ex ante usa D=14; Borracchi&Giglio usan gamma=0.33 (~3 dias), valor de marzo 2020 hoy considerado bajo.
B13: IFR base pre-vacunacion | C13: 0.006 | D13: 0.004 | E13: 0.009 | F13: fraccion | G13: Meta-analisis de seroprevalencia. CRITICO: es IFR (sobre infecciones), no CFR (sobre casos). El analisis ex ante aplica CFR de Wu&McGoogan (2020) a los infectados del SIR, lo que sobrestima la mortalidad.
B14: Rezago infeccion -> muerte | C14: 3 | D14: 2 | E14: 3 | F14: semanas | G14: 19 dias segun meta-analisis, redondeado a 3 semanas por el paso del modelo.
B15: Efectividad vacunal contra muerte | C15: 0.7 | D15: 0.6 | E15: 0.8 | F15: fraccion | G15: Promedio ponderado del mix argentino. Lancet Reg Health Am (2023), test-negative, 83.708 hospitalizados AR/BR/CL/CO. Ver hoja Fuentes.
B17: PARAMETROS DERIVADOS
B18: gamma (tasa de recuperacion, semanal) | C18: =7/Parametros!$C$12 -> 0.7 | F18: 1/semana | G18: Calculado como 7 dias / D. Con D=10 dias, gamma = 0.70 por semana.
B19: S0 (susceptibles iniciales) | C19: =Parametros!$C$6*Parametros!$C$7-Parametros!$C$8 -> 45510224 | F19: personas
B21: ATRIBUCION AL PRESTAMO (para efectividad / eficiencia)
B22: Dosis financiadas por el prestamo | C22: 22459300 | F22: dosis | G22: Producto 3.40, matriz de productos AR-L1326. Dato verificado.
B23: Dosis totales aplicadas en Argentina | C23: 104164884 | F23: dosis | G23: OWID 'total_vaccinations' al 05-jun-2022. Dato verificado.
B24: Fraccion atribuible al prestamo | C24: =Parametros!$C$22/Parametros!$C$23 -> 0.21561297 | F24: fraccion | G24: ADVERTENCIA: el prorrateo lineal supone efecto marginal igual para toda dosis. No es cierto: las primeras dosis fueron a grupos priorizados (60+, personal de salud) y evitaron mas muertes por dosis. Usar como estimacion CONSERVADORA.
B25: Muertes evitadas por vacunacion en Argentina | F25: muertes | G25: PENDIENTE: extraer de la Tabla 1 de Open Forum Infect Dis 2024;11(10):ofae528. NO prorratear el total regional (610k-2.61M para 17 paises) por poblacion.
B26: Muertes evitadas atribuibles al prestamo | C26: =IF(Parametros!$C$25="","",Parametros!$C$25*Parametros!$C$24) | G26: Se completa automaticamente al cargar la celda anterior.
B28: LEYENDA
B29: Celda con relleno amarillo: pendiente de completar
B30: Celda con relleno azul: parametro clave para sensibilidad

Sheet Tramos_Beta
B2: BETA(t) POR TRAMOS DE POLITICA
B3: Cronologia de NPI segun Romo & Ojeda-Galaviz (2021) Fig.10, IJERPH 18(1):73, complementada con hitos de ejecucion del prestamo.
B5: # | C5: Hito de politica | D5: Fecha inicio | E5: Semana ini | F5: Semana fin | G5: beta | H5: R0 efectivo | I5: Fuente
B6: 1 | C6: Pre-intervencion | D6: 43898 | E6: 1 | F6: =F7-1 -> 110 | G6: 2 | H6: =G6/Parametros!$C$18 -> 2.8571429 | I6: Primer caso 03-mar-2020
B7: 2 | C7: Cierre fronteras + ASPO (Dto 297/20) | D7: 43906 | E7: 2 | F7: =F8-1 -> 111 | G7: 1.6598 | H7: =G7/Parametros!$C$18 -> 2.3711429 | I7: IJERPH Fig.10. Agrupa 4 medidas del 12 al 20-mar: el paso semanal no las resuelve.
B8: 3 | C8: DISPO / flexibilizacion | D8: 43983 | E8: 13 | F8: =F9-1 -> 112 | G8: 0.7636 | H8: =G8/Parametros!$C$18 -> 1.0908571 | I8: Contexto
B9: 4 | C9: Relajamiento primavera-verano | D9: 44136 | E9: 35 | F9: =F10-1 -> 113 | G9: 0.734 | H9: =G9/Parametros!$C$18 -> 1.0485714 | I9: Contexto
B10: 5 | C10: Inicio vacunacion | D10: 44194 | E10: 43 | F10: =F11-1 -> 114 | G10: 1.0661 | H10: =G10/Parametros!$C$18 -> 1.523 | I10: OWID
B11: 6 | C11: Segunda ola / restricciones | D11: 44287 | E11: 56 | F11: =F12-1 -> 115 | G11: 0.9094 | H11: =G11/Parametros!$C$18 -> 1.2991429 | I11: Contexto
B12: 7 | C12: Vacunacion masiva | D12: 44378 | E12: 69 | F12: =F13-1 -> 116 | G12: 1.0526 | H12: =G12/Parametros!$C$18 -> 1.5037143 | I12: MdR ind. 3.3
B13: 8 | C13: Omicron | D13: 44531 | E13: 91 | F13: =F14-1 -> 117 | G13: 1.2696 | H13: =G13/Parametros!$C$18 -> 1.8137143 | I13: Contexto
B14: 9 | C14: Post-Omicron | D14: 44621 | E14: 104 | F14: 118 | G14: 0.815 | H14: =G14/Parametros!$C$18 -> 1.1642857 | I14: Contexto
B16: Los valores de beta en amarillo son los que ajusta el Solver. Los valores actuales YA ESTAN CALIBRADOS (L-BFGS-B sobre la serie de mortalidad): SSE=163.0, error en muertes acumuladas -13.9%, tasa de ataque 42.9%.
B17: NOTA: las medidas del 12 al 20-mar-2020 (suspension de actividades, cierre de fronteras, ASPO) se agrupan en un solo tramo: ocurrieron en 12 dias y el paso semanal no permite identificarlas por separado.
B18: R0 efectivo = beta / gamma. Interpretacion: casos secundarios por caso en poblacion totalmente susceptible.

Sheet Datos_OWID
B2: DATOS OBSERVADOS — OUR WORLD IN DATA
B3: Argentina, agregacion semanal (domingo). Descargado de github.com/owid/covid-19-data. Serie: 08-mar-2020 a 05-jun-2022.
B5: Semana | C5: Fecha | D5: Casos | E5: Muertes | F5: Tests | G5: Positividad | H5: Rt OWID | I5: Vacunados compl.
B6: 1 | C6: 43898 | D6: 22 | E6: 1 | F6: 45.5 | G6: 0.10333333 | I6: 0
B7: 2 | C7: 43905 | D7: 109 | E7: 8 | F7: 204 | G7: 0.21 | I7: 0
B8: 3 | C8: 43912 | D8: 405 | E8: 11 | F8: 867 | G8: 0.16 | H8: 2.375 | I8: 0
B9: 4 | C9: 43919 | D9: 746 | E9: 50 | F9: 2551 | G9: 0.23714286 | H9: 1.9671429 | I9: 0
B10: 5 | C10: 43926 | D10: 791 | E10: 61 | F10: 5891 | G10: 0.17571429 | H10: 1.4657143 | I10: 0
B11: 6 | C11: 43933 | D11: 917 | E11: 74 | F11: 10760 | G11: 0.10285714 | H11: 1.1542857 | I11: 0
B12: 7 | C12: 43940 | D12: 1076 | E12: 74 | F12: 13754 | G12: 0.092857143 | H12: 1.1371429 | I12: 0
B13: 8 | C13: 43947 | D13: 1398 | E13: 132 | F13: 16997 | G13: 0.085714286 | H13: 1.24 | I13: 0
B14: 9 | C14: 43954 | D14: 1289 | E14: 115 | F14: 18485 | G14: 0.085714286 | H14: 1.0685714 | I14: 0
B15: 10 | C15: 43961 | D15: 1897 | E15: 120 | F15: 22188 | G15: 0.08 | H15: 1.2685714 | I15: 0
B16: 11 | C16: 43968 | D16: 2910 | E16: 144 | F16: 25877 | G16: 0.1 | H16: 1.43 | I16: 0
B17: 12 | C17: 43975 | D17: 5061 | E17: 219 | F17: 32115 | G17: 0.12285714 | H17: 1.5542857 | I17: 0
B18: 13 | C18: 43982 | D18: 5785 | E18: 297 | F18: 36128 | G18: 0.15428571 | H18: 1.3371429 | I18: 0
B19: 14 | C19: 43989 | D19: 7297 | E19: 358 | F19: 40385 | G19: 0.17 | H19: 1.2657143 | I19: 0
... B123: 118 | C123: 44717 | D123: 0 | E123: 0 | F123: 259775.83 | G123: 0.29 | H123: 0.23833333 | I123: 34593479
B125: Total muertes en la serie: 128,889 | Total casos: 9,230,573 | Positividad maxima: 65%
B126: La positividad supero ampliamente el umbral OMS de 5%, lo que confirma subregistro severo y justifica calibrar contra mortalidad.

Sheet Modelo_SIRD
B2: MODELO SIRD — INTEGRACION DE EULER (PASO SEMANAL)
B3: dS/dt = -beta*S*I/N | dI/dt = beta*S*I/N - gamma*I | dR/dt = gamma*(1-ifr)*I | dD/dt = gamma*ifr*I
B4: La mortalidad se modela como fraccion de las SALIDAS del compartimento I, no como tasa independiente: asi gamma controla la duracion y el IFR la severidad.
B5: NO EDITAR las columnas D a N: son formulas. Para cambiar el modelo, editar Parametros o Tramos_Beta.
B7: Sem | C7: Fecha | D7: beta(t) | E7: Cobertura vac. | F7: IFR(t) | G7: S | H7: I | I7: R | J7: D | K7: Nuevas infecc. | L7: Muertes sem. | M7: Muertes c/rezago | N7: Rt
B8: =Datos_OWID!B6 -> 1 | C8: =Datos_OWID!C6 -> 43898 | D8: =IFERROR(INDEX(Tramos_Beta!$G$6:$G$14,MATCH(B8,Tramos_Beta!$E$6:$E$14,1)),INDEX(Tramos_Beta!$G$6:$G$14,1)) -> 2 | E8: =Datos_OWID!I6/Parametros!$C$6 -> 0 | F8: =Parametros!$C$13*(1-E8*Parametros!$C$15) -> 0.006 | G8: =Parametros!$C$19 -> 45510224 | H8: =Parametros!$C$8 -> 100 | I8: 0 | J8: 0 | K8: =Parametros!$C$8 -> 100 | L8: 0 | M8: =IF(B8<=Parametros!$C$14,0,INDEX($L$8:$L$125,B8-Parametros!$C$14)) -> 0 | N8: =D8/Parametros!$C$18*G8/Parametros!$C$6 -> 2.8571366
B9: =Datos_OWID!B7 -> 2 | C9: =Datos_OWID!C7 -> 43905 | D9: =IFERROR(INDEX(Tramos_Beta!$G$6:$G$14,MATCH(B9,Tramos_Beta!$E$6:$E$14,1)),INDEX(Tramos_Beta!$G$6:$G$14,1)) -> 1.6598 | E9: =Datos_OWID!I7/Parametros!$C$6 -> 0 | F9: =Parametros!$C$13*(1-E9*Parametros!$C$15) -> 0.006 | G9: =MAX(0,G8-D8*G8*H8/Parametros!$C$6) -> 45510024 | H9: =MAX(0,H8+D8*G8*H8/Parametros!$C$6-Parametros!$C$18*H8) -> 229.99956 | I9: =I8+Parametros!$C$18*(1-F8)*H8 -> 69.58 | J9: =J8+Parametros!$C$18*F8*H8 -> 0.42 | K9: =MAX(0,G8-G9) -> 199.99956 | L9: =J9-J8 -> 0.42 | M9: =IF(B9<=Parametros!$C$14,0,INDEX($L$8:$L$125,B9-Parametros!$C$14)) -> 0 | N9: =D9/Parametros!$C$18*G9/Parametros!$C$6 -> 2.3711272
B10: =Datos_OWID!B8 -> 3 | C10: =Datos_OWID!C8 -> 43912 | D10: =IFERROR(INDEX(Tramos_Beta!$G$6:$G$14,MATCH(B10,Tramos_Beta!$E$6:$E$14,1)),INDEX(Tramos_Beta!$G$6:$G$14,1)) -> 1.6598 | E10: =Datos_OWID!I8/Parametros!$C$6 -> 0 | F10: =Parametros!$C$13*(1-E10*Parametros!$C$15) -> 0.006 | G10: =MAX(0,G9-D9*G9*H9/Parametros!$C$6) -> 45509642 | H10: =MAX(0,H9+D9*G9*H9/Parametros!$C$6-Parametros!$C$18*H9) -> 450.75062 | I10: =I9+Parametros!$C$18*(1-F9)*H9 -> 229.61369 | J10: =J9+Parametros!$C$18*F9*H9 -> 1.3859982 | K10: =MAX(0,G9-G10) -> 381.75075 | L10: =J10-J9 -> 0.96599815 | M10: =IF(B10<=Parametros!$C$14,0,INDEX($L$8:$L$125,B10-Parametros!$C$14)) -> 0 | N10: =D10/Parametros!$C$18*G10/Parametros!$C$6 -> 2.3711073
B11: =Datos_OWID!B9 -> 4 | C11: =Datos_OWID!C9 -> 43919 | D11: =IFERROR(INDEX(Tramos_Beta!$G$6:$G$14,MATCH(B11,Tramos_Beta!$E$6:$E$14,1)),INDEX(Tramos_Beta!$G$6:$G$14,1)) -> 1.6598 | E11: =Datos_OWID!I9/Parametros!$C$6 -> 0 | F11: =Parametros!$C$13*(1-E11*Parametros!$C$15) -> 0.006 | G11: =MAX(0,G10-D10*G10*H10/Parametros!$C$6) -> 45508894 | H11: =MAX(0,H10+D10*G10*H10/Parametros!$C$6-Parametros!$C$18*H10) -> 883.36986 | I11: =I10+Parametros!$C$18*(1-F10)*H10 -> 543.24598 | J11: =J10+Parametros!$C$18*F10*H10 -> 3.2791508 | K11: =MAX(0,G10-G11) -> 748.14468 | L11: =J11-J10 -> 1.8931526 | M11: =IF(B11<=Parametros!$C$14,0,INDEX($L$8:$L$125,B11-Parametros!$C$14)) -> 0 | N11: =D11/Parametros!$C$18*G11/Parametros!$C$6 -> 2.3710684
B12: =Datos_OWID!B10 -> 5 | C12: =Datos_OWID!C10 -> 43926 | D12: =IFERROR(INDEX(Tramos_Beta!$G$6:$G$14,MATCH(B12,Tramos_Beta!$E$6:$E$14,1)),INDEX(Tramos_Beta!$G$6:$G$14,1)) -> 1.6598 | E12: =Datos_OWID!I10/Parametros!$C$6 -> 0 | F12: =Parametros!$C$13*(1-E12*Parametros!$C$15) -> 0.006 | G12: =MAX(0,G11-D11*G11*H11/Parametros!$C$6) -> 45507428 | H12: =MAX(0,H11+D11*G11*H11/Parametros!$C$6-Parametros!$C$18*H11) -> 1731.1822 | I12: =I11+Parametros!$C$18*(1-F11)*H11 -> 1157.8947 | J12: =J11+Parametros!$C$18*F11*H11 -> 6.9893042 | K12: =MAX(0,G11-G12) -> 1466.1712 | L12: =J12-J11 -> 3.7101534 | M12: =IF(B12<=Parametros!$C$14,0,INDEX($L$8:$L$125,B12-Parametros!$C$14)) -> 0.42 | N12: =D12/Parametros!$C$18*G12/Parametros!$C$6 -> 2.370992
B13: =Datos_OWID!B11 -> 6 | C13: =Datos_OWID!C11 -> 43933 | D13: =IFERROR(INDEX(Tramos_Beta!$G$6:$G$14,MATCH(B13,Tramos_Beta!$E$6:$E$14,1)),INDEX(Tramos_Beta!$G$6:$G$14,1)) -> 1.6598 | E13: =Datos_OWID!I11/Parametros!$C$6 -> 0 | F13: =Parametros!$C$13*(1-E13*Parametros!$C$15) -> 0.006 | G13: =MAX(0,G12-D12*G12*H12/Parametros!$C$6) -> 45504555 | H13: =MAX(0,H12+D12*G12*H12/Parametros!$C$6-Parametros!$C$18*H12) -> 3392.588 | I13: =I12+Parametros!$C$18*(1-F12)*H12 -> 2362.4513 | J13: =J12+Parametros!$C$18*F12*H12 -> 14.260269 | K13: =MAX(0,G12-G13) -> 2873.2333 | L13: =J13-J12 -> 7.2709652 | M13: =IF(B13<=Parametros!$C$14,0,INDEX($L$8:$L$125,B13-Parametros!$C$14)) -> 0.96599815 | N13: =D13/Parametros!$C$18*G13/Parametros!$C$6 -> 2.3708423
B14: =Datos_OWID!B12 -> 7 | C14: =Datos_OWID!C12 -> 43940 | D14: =IFERROR(INDEX(Tramos_Beta!$G$6:$G$14,MATCH(B14,Tramos_Beta!$E$6:$E$14,1)),INDEX(Tramos_Beta!$G$6:$G$14,1)) -> 1.6598 | E14: =Datos_OWID!I12/Parametros!$C$6 -> 0 | F14: =Parametros!$C$13*(1-E14*Parametros!$C$15) -> 0.006 | G14: =MAX(0,G13-D13*G13*H13/Parametros!$C$6) -> 45498924 | H14: =MAX(0,H13+D13*G13*H13/Parametros!$C$6-Parametros!$C$18*H13) -> 6648.0801 | I14: =I13+Parametros!$C$18*(1-F13)*H13 -> 4723.014 | J14: =J13+Parametros!$C$18*F13*H13 -> 28.509139 | K14: =MAX(0,G13-G14) -> 5630.3037 | L14: =J14-J13 -> 14.24887 | M14: =IF(B14<=Parametros!$C$14,0,INDEX($L$8:$L$125,B14-Parametros!$C$14)) -> 1.8931526 | N14: =D14/Parametros!$C$18*G14/Parametros!$C$6 -> 2.3705489
B15: =Datos_OWID!B13 -> 8 | C15: =Datos_OWID!C13 -> 43947 | D15: =IFERROR(INDEX(Tramos_Beta!$G$6:$G$14,MATCH(B15,Tramos_Beta!$E$6:$E$14,1)),INDEX(Tramos_Beta!$G$6:$G$14,1)) -> 1.6598 | E15: =Datos_OWID!I13/Parametros!$C$6 -> 0 | F15: =Parametros!$C$13*(1-E15*Parametros!$C$15) -> 0.006 | G15: =MAX(0,G14-D14*G14*H14/Parametros!$C$6) -> 45487893 | H15: =MAX(0,H14+D14*G14*H14/Parametros!$C$6-Parametros!$C$18*H14) -> 13026.143 | I15: =I14+Parametros!$C$18*(1-F14)*H14 -> 9348.7482 | J15: =J14+Parametros!$C$18*F14*H14 -> 56.431076 | K15: =MAX(0,G14-G15) -> 11031.719 | L15: =J15-J14 -> 27.921937 | M15: =IF(B15<=Parametros!$C$14,0,INDEX($L$8:$L$125,B15-Parametros!$C$14)) -> 3.7101534 | N15: =D15/Parametros!$C$18*G15/Parametros!$C$6 -> 2.3699742
B16: =Datos_OWID!B14 -> 9 | C16: =Datos_OWID!C14 -> 43954 | D16: =IFERROR(INDEX(Tramos_Beta!$G$6:$G$14,MATCH(B16,Tramos_Beta!$E$6:$E$14,1)),INDEX(Tramos_Beta!$G$6:$G$14,1)) -> 1.6598 | E16: =Datos_OWID!I14/Parametros!$C$6 -> 0 | F16: =Parametros!$C$13*(1-E16*Parametros!$C$15) -> 0.006 | G16: =MAX(0,G15-D15*G15*H15/Parametros!$C$6) -> 45466283 | H16: =MAX(0,H15+D15*G15*H15/Parametros!$C$6-Parametros!$C$18*H15) -> 25517.979 | I16: =I15+Parametros!$C$18*(1-F15)*H15 -> 18412.339 | J16: =J15+Parametros!$C$18*F15*H15 -> 111.14088 | K16: =MAX(0,G15-G16) -> 21610.136 | L16: =J16-J15 -> 54.709803 | M16: =IF(B16<=Parametros!$C$14,0,INDEX($L$8:$L$125,B16-Parametros!$C$14)) -> 7.2709652 | N16: =D16/Parametros!$C$18*G16/Parametros!$C$6 -> 2.3688482
B17: =Datos_OWID!B15 -> 10 | C17: =Datos_OWID!C15 -> 43961 | D17: =IFERROR(INDEX(Tramos_Beta!$G$6:$G$14,MATCH(B17,Tramos_Beta!$E$6:$E$14,1)),INDEX(Tramos_Beta!$G$6:$G$14,1)) -> 1.6598 | E17: =Datos_OWID!I15/Parametros!$C$6 -> 0 | F17: =Parametros!$C$13*(1-E17*Parametros!$C$15) -> 0.006 | G17: =MAX(0,G16-D16*G16*H16/Parametros!$C$6) -> 45423969 | H17: =MAX(0,H16+D16*G16*H16/Parametros!$C$6-Parametros!$C$18*H16) -> 49969.148 | I17: =I16+Parametros!$C$18*(1-F16)*H16 -> 36167.749 | J17: =J16+Parametros!$C$18*F16*H16 -> 218.31639 | K17: =MAX(0,G16-G17) -> 42313.755 | L17: =J17-J16 -> 107.17551 | M17: =IF(B17<=Parametros!$C$14,0,INDEX($L$8:$L$125,B17-Parametros!$C$14)) -> 14.24887 | N17: =D17/Parametros!$C$18*G17/Parametros!$C$6 -> 2.3666436
B18: =Datos_OWID!B16 -> 11 | C18: =Datos_OWID!C16 -> 43968 | D18: =IFERROR(INDEX(Tramos_Beta!$G$6:$G$14,MATCH(B18,Tramos_Beta!$E$6:$E$14,1)),INDEX(Tramos_Beta!$G$6:$G$14,1)) -> 1.6598 | E18: =Datos_OWID!I16/Parametros!$C$6 -> 0 | F18: =Parametros!$C$13*(1-E18*Parametros!$C$15) -> 0.006 | G18: =MAX(0,G17-D17*G17*H17/Parametros!$C$6) -> 45341187 | H18: =MAX(0,H17+D17*G17*H17/Parametros!$C$6-Parametros!$C$18*H17) -> 97772.162 | I18: =I17+Parametros!$C$18*(1-F17)*H17 -> 70936.282 | J18: =J17+Parametros!$C$18*F17*H17 -> 428.18681 | K18: =MAX(0,G17-G18) -> 82781.417 | L18: =J18-J17 -> 209.87042 | M18: =IF(B18<=Parametros!$C$14,0,INDEX($L$8:$L$125,B18-Parametros!$C$14)) -> 27.921937 | N18: =D18/Parametros!$C$18*G18/Parametros!$C$6 -> 2.3623306
B19: =Datos_OWID!B17 -> 12 | C19: =Datos_OWID!C17 -> 43975 | D19: =IFERROR(INDEX(Tramos_Beta!$G$6:$G$14,MATCH(B19,Tramos_Beta!$E$6:$E$14,1)),INDEX(Tramos_Beta!$G$6:$G$14,1)) -> 1.6598 | E19: =Datos_OWID!I17/Parametros!$C$6 -> 0 | F19: =Parametros!$C$13*(1-E19*Parametros!$C$15) -> 0.006 | G19: =MAX(0,G18-D18*G18*H18/Parametros!$C$6) -> 45179508 | H19: =MAX(0,H18+D18*G18*H18/Parametros!$C$6-Parametros!$C$18*H18) -> 191010.77 | I19: =I18+Parametros!$C$18*(1-F18)*H18 -> 138966.15 | J19: =J18+Parametros!$C$18*F18*H18 -> 838.82989 | K19: =MAX(0,G18-G19) -> 161679.12 | L19: =J19-J18 -> 410.64308 | M19: =IF(B19<=Parametros!$C$14,0,INDEX($L$8:$L$125,B19-Parametros!$C$14)) -> 54.709803 | N19: =D19/Parametros!$C$18*G19/Parametros!$C$6 -> 2.353907
B20: =Datos_OWID!B18 -> 13 | C20: =Datos_OWID!C18 -> 43982 | D20: =IFERROR(INDEX(Tramos_Beta!$G$6:$G$14,MATCH(B20,Tramos_Beta!$E$6:$E$14,1)),INDEX(Tramos_Beta!$G$6:$G$14,1)) -> 0.7636 | E20: =Datos_OWID!I18/Parametros!$C$6 -> 0 | F20: =Parametros!$C$13*(1-E20*Parametros!$C$15) -> 0.006 | G20: =MAX(0,G19-D19*G19*H19/Parametros!$C$6) -> 44864773 | H20: =MAX(0,H19+D19*G19*H19/Parametros!$C$6-Parametros!$C$18*H19) -> 372038.34 | I20: =I19+Parametros!$C$18*(1-F19)*H19 -> 271871.45 | J20: =J19+Parametros!$C$18*F19*H19 -> 1641.0751 | K20: =MAX(0,G19-G20) -> 314735.11 | L20: =J20-J19 -> 802.24523 | M20: =IF(B20<=Parametros!$C$14,0,INDEX($L$8:$L$125,B20-Parametros!$C$14)) -> 107.17551 | N20: =D20/Parametros!$C$18*G20/Parametros!$C$6 -> 1.0753836
... B125: =Datos_OWID!B123 -> 118 | C125: =Datos_OWID!C123 -> 44717 | D125: =IFERROR(INDEX(Tramos_Beta!$G$6:$G$14,MATCH(B125,Tramos_Beta!$E$6:$E$14,1)),INDEX(Tramos_Beta!$G$6:$G$14,1)) -> 0.815 | E125: =Datos_OWID!I123/Parametros!$C$6 -> 0.76012377 | F125: =Parametros!$C$13*(1-E125*Parametros!$C$15) -> 0.0028074802 | G125: =MAX(0,G124-D124*G124*H124/Parametros!$C$6) -> 26000653 | H125: =MAX(0,H124+D124*G124*H124/Parametros!$C$6-Parametros!$C$18*H124) -> 2377.4495 | I125: =I124+Parametros!$C$18*(1-F124)*H124 -> 19396292 | J125: =J124+Parametros!$C$18*F124*H124 -> 111001.43 | K125: =MAX(0,G124-G125) -> 1445.9033 | L125: =J125-J124 -> 6.1065677 | M125: =IF(B125<=Parametros!$C$14,0,INDEX($L$8:$L$125,B125-Parametros!$C$14)) -> 13.64329 | N125: =D125/Parametros!$C$18*G125/Parametros!$C$6 -> 0.66517191
B127: TOTALES
B128: Infecciones acumuladas (modelo) | D128: =Parametros!$C$19-G125 -> 19509571
B129: Muertes acumuladas (modelo) | D129: =J125 -> 111001.43
B130: Muertes acumuladas (observadas) | D130: =SUM(Datos_OWID!E6:E123) -> 128889
B131: Tasa de ataque (infectados / poblacion) | D131: =Modelo_SIRD!$D$128/Parametros!$C$6 -> 0.4286845
B132: Factor de subregistro (infecciones modelo / casos reportados) | D132: =Modelo_SIRD!$D$128/SUM(Datos_OWID!D6:D123) -> 2.1135817
B133: Referencia: 8.5 (mediana de 91 paises, Rahmandad et al. 2020). Un valor muy alejado sugiere revisar el IFR.

Sheet Deteccion
B2: TASA DE DETECCION IMPLICITA
B3: Metrica clave para vincular el Componente 2 (Producto 2.20: 35 laboratorios equipados) con el Resultado 2.1.
B4: Deteccion = casos reportados / infecciones estimadas por el modelo.
B6: Sem | C6: Fecha | D6: Casos reportados | E6: Infecc. modelo | F6: Tasa deteccion | G6: Positividad | H6: Tests
B7: =Datos_OWID!B6 -> 1 | C7: =Datos_OWID!C6 -> 43898 | D7: =Datos_OWID!D6 -> 22 | E7: =Modelo_SIRD!K8 -> 100 | F7: =IF(E7<=0,"",MIN(1,D7/E7)) -> 0.22 | G7: =Datos_OWID!G6 -> 0.10333333 | H7: =Datos_OWID!F6 -> 45.5
B8: =Datos_OWID!B7 -> 2 | C8: =Datos_OWID!C7 -> 43905 | D8: =Datos_OWID!D7 -> 109 | E8: =Modelo_SIRD!K9 -> 199.99956 | F8: =IF(E8<=0,"",MIN(1,D8/E8)) -> 0.5450012 | G8: =Datos_OWID!G7 -> 0.21 | H8: =Datos_OWID!F7 -> 204
B9: =Datos_OWID!B8 -> 3 | C9: =Datos_OWID!C8 -> 43912 | D9: =Datos_OWID!D8 -> 405 | E9: =Modelo_SIRD!K10 -> 381.75075 | F9: =IF(E9<=0,"",MIN(1,D9/E9)) -> 1 | G9: =Datos_OWID!G8 -> 0.16 | H9: =Datos_OWID!F8 -> 867
B10: =Datos_OWID!B9 -> 4 | C10: =Datos_OWID!C9 -> 43919 | D10: =Datos_OWID!D9 -> 746 | E10: =Modelo_SIRD!K11 -> 748.14468 | F10: =IF(E10<=0,"",MIN(1,D10/E10)) -> 0.99713334 | G10: =Datos_OWID!G9 -> 0.23714286 | H10: =Datos_OWID!F9 -> 2551
B11: =Datos_OWID!B10 -> 5 | C11: =Datos_OWID!C10 -> 43926 | D11: =Datos_OWID!D10 -> 791 | E11: =Modelo_SIRD!K12 -> 1466.1712 | F11: =IF(E11<=0,"",MIN(1,D11/E11)) -> 0.53950042 | G11: =Datos_OWID!G10 -> 0.17571429 | H11: =Datos_OWID!F10 -> 5891
B12: =Datos_OWID!B11 -> 6 | C12: =Datos_OWID!C11 -> 43933 | D12: =Datos_OWID!D11 -> 917 | E12: =Modelo_SIRD!K13 -> 2873.2333 | F12: =IF(E12<=0,"",MIN(1,D12/E12)) -> 0.31915264 | G12: =Datos_OWID!G11 -> 0.10285714 | H12: =Datos_OWID!F11 -> 10760
B13: =Datos_OWID!B12 -> 7 | C13: =Datos_OWID!C12 -> 43940 | D13: =Datos_OWID!D12 -> 1076 | E13: =Modelo_SIRD!K14 -> 5630.3037 | F13: =IF(E13<=0,"",MIN(1,D13/E13)) -> 0.1911087 | G13: =Datos_OWID!G12 -> 0.092857143 | H13: =Datos_OWID!F12 -> 13754
B14: =Datos_OWID!B13 -> 8 | C14: =Datos_OWID!C13 -> 43947 | D14: =Datos_OWID!D13 -> 1398 | E14: =Modelo_SIRD!K15 -> 11031.719 | F14: =IF(E14<=0,"",MIN(1,D14/E14)) -> 0.12672549 | G14: =Datos_OWID!G13 -> 0.085714286 | H14: =Datos_OWID!F13 -> 16997
B15: =Datos_OWID!B14 -> 9 | C15: =Datos_OWID!C14 -> 43954 | D15: =Datos_OWID!D14 -> 1289 | E15: =Modelo_SIRD!K16 -> 21610.136 | F15: =IF(E15<=0,"",MIN(1,D15/E15)) -> 0.059647935 | G15: =Datos_OWID!G14 -> 0.085714286 | H15: =Datos_OWID!F14 -> 18485
B16: =Datos_OWID!B15 -> 10 | C16: =Datos_OWID!C15 -> 43961 | D16: =Datos_OWID!D15 -> 1897 | E16: =Modelo_SIRD!K17 -> 42313.755 | F16: =IF(E16<=0,"",MIN(1,D16/E16)) -> 0.044831758 | G16: =Datos_OWID!G15 -> 0.08 | H16: =Datos_OWID!F15 -> 22188
B17: =Datos_OWID!B16 -> 11 | C17: =Datos_OWID!C16 -> 43968 | D17: =Datos_OWID!D16 -> 2910 | E17: =Modelo_SIRD!K18 -> 82781.417 | F17: =IF(E17<=0,"",MIN(1,D17/E17)) -> 0.035152817 | G17: =Datos_OWID!G16 -> 0.1 | H17: =Datos_OWID!F16 -> 25877
B18: =Datos_OWID!B17 -> 12 | C18: =Datos_OWID!C17 -> 43975 | D18: =Datos_OWID!D17 -> 5061 | E18: =Modelo_SIRD!K19 -> 161679.12 | F18: =IF(E18<=0,"",MIN(1,D18/E18)) -> 0.031302743 | G18: =Datos_OWID!G17 -> 0.12285714 | H18: =Datos_OWID!F17 -> 32115
... B124: =Datos_OWID!B123 -> 118 | C124: =Datos_OWID!C123 -> 44717 | D124: =Datos_OWID!D123 -> 0 | E124: =Modelo_SIRD!K125 -> 1445.9033 | F124: =IF(E124<=0,"",MIN(1,D124/E124)) -> 0 | G124: =Datos_OWID!G123 -> 0.29 | H124: =Datos_OWID!F123 -> 259775.83
B126: RESUMEN POR PERIODO
B127: Los cortes reflejan la cronologia de equipamiento de laboratorios del Componente 2 (17 labs en 2020, 35 acumulados en 2021).
B128: Periodo | C128: Sem. desde | D128: Sem. hasta | E128: Deteccion media | F128: Positividad media | G128: Tests promedio
B129: 1. Mar-Jun 2020 (pre-ampliacion de red) | C129: 1 | D129: 17 | E129: =AVERAGEIFS($F$7:$F$124,$B$7:$B$124,">="&C129,$B$7:$B$124,"<="&D129) -> 0.25274464 | F129: =AVERAGEIFS($G$7:$G$124,$B$7:$B$124,">="&C129,$B$7:$B$124,"<="&D129) -> 0.15170868 | G129: =AVERAGEIFS($H$7:$H$124,$B$7:$B$124,">="&C129,$B$7:$B$124,"<="&D129) -> 23563.382
B130: 2. Jul-Dic 2020 (17 labs equipados) | C130: 18 | D130: 43 | E130: =AVERAGEIFS($F$7:$F$124,$B$7:$B$124,">="&C130,$B$7:$B$124,"<="&D130) -> 0.25566334 | F130: =AVERAGEIFS($G$7:$G$124,$B$7:$B$124,">="&C130,$B$7:$B$124,"<="&D130) -> 0.31807692 | G130: =AVERAGEIFS($H$7:$H$124,$B$7:$B$124,">="&C130,$B$7:$B$124,"<="&D130) -> 171943
B131: 3. Ene-Jun 2021 (35 labs equipados) | C131: 44 | D131: 69 | E131: =AVERAGEIFS($F$7:$F$124,$B$7:$B$124,">="&C131,$B$7:$B$124,"<="&D131) -> 0.43375635 | F131: =AVERAGEIFS($G$7:$G$124,$B$7:$B$124,">="&C131,$B$7:$B$124,"<="&D131) -> 0.20335165 | G131: =AVERAGEIFS($H$7:$H$124,$B$7:$B$124,">="&C131,$B$7:$B$124,"<="&D131) -> 452234.42
B132: 4. Jul-Dic 2021 | C132: 70 | D132: 95 | E132: =AVERAGEIFS($F$7:$F$124,$B$7:$B$124,">="&C132,$B$7:$B$124,"<="&D132) -> 0.42357167 | F132: =AVERAGEIFS($G$7:$G$124,$B$7:$B$124,">="&C132,$B$7:$B$124,"<="&D132) -> 0.075989011 | G132: =AVERAGEIFS($H$7:$H$124,$B$7:$B$124,">="&C132,$B$7:$B$124,"<="&D132) -> 423923.92
B133: 5. 2022 (Omicron) | C133: 96 | D133: 118 | E133: =AVERAGEIFS($F$7:$F$124,$B$7:$B$124,">="&C133,$B$7:$B$124,"<="&D133) -> 0.90081069 | F133: =AVERAGEIFS($G$7:$G$124,$B$7:$B$124,">="&C133,$B$7:$B$124,"<="&D133) -> 0.23130435 | G133: =AVERAGEIFS($H$7:$H$124,$B$7:$B$124,">="&C133,$B$7:$B$124,"<="&D133) -> 390363.34
B135: CONTRAFACTUAL DE DETECCION
B136: Supuesto: la tasa de deteccion se hubiera mantenido en el nivel del periodo 1 (previo a la ampliacion de la red de laboratorios).
B137: Deteccion de referencia (periodo 1) | E137: =E129 -> 0.25274464
B138: Infecciones estimadas desde la semana 18 | E138: =SUMIF($B$7:$B$124,">17",$E$7:$E$124) -> 17669966
B139: Casos que se habrian detectado a la tasa de referencia | E139: =Deteccion!$E$138*Deteccion!$E$137 -> 4465989.2
B140: Casos efectivamente detectados desde la semana 18 | E140: =SUMIF($B$7:$B$124,">17",$D$7:$D$124) -> 9157128
B141: Casos adicionales detectados por la capacidad ampliada | E141: =MAX(0,Deteccion!$E$140-Deteccion!$E$139) -> 4691138.8
B143: ADVERTENCIA: este contrafactual atribuye TODA la mejora de deteccion a la ampliacion de la red de laboratorios.
B144: Argentina amplio capacidad por multiples vias (tests de antigenos, laboratorios privados, financiamiento propio). El prestamo financio 35 labs sobre una red mayor.
B145: DECLARAR como cota superior, no como estimacion central.
B147: LECTURA PARA EL PCR
B148: El salto de deteccion entre el periodo 2 (17 labs) y el periodo 3 (35 labs) es el dato relevante para el Componente 2. Comparar ambas filas del resumen.

Sheet Calibracion
B2: CALIBRACION DEL MODELO
B4: FUNCION OBJETIVO
B5: Error cuadratico sobre log(muertes+1). El log pondera proporcionalmente y evita que las olas grandes dominen el ajuste de las pequenas.
B7: Sem | C7: Muertes obs. | D7: Muertes modelo | E7: log(obs+1) | F7: log(mod+1) | G7: Error^2
B8: =Datos_OWID!B6 -> 1 | C8: =Datos_OWID!E6 -> 1 | D8: =Modelo_SIRD!M8 -> 0 | E8: =LN(C8+1) -> 0.69314718 | F8: =LN(D8+1) -> 0 | G8: =(E8-F8)^2 -> 0.48045301
B9: =Datos_OWID!B7 -> 2 | C9: =Datos_OWID!E7 -> 8 | D9: =Modelo_SIRD!M9 -> 0 | E9: =LN(C9+1) -> 2.1972246 | F9: =LN(D9+1) -> 0 | G9: =(E9-F9)^2 -> 4.8277958
B10: =Datos_OWID!B8 -> 3 | C10: =Datos_OWID!E8 -> 11 | D10: =Modelo_SIRD!M10 -> 0 | E10: =LN(C10+1) -> 2.4849066 | F10: =LN(D10+1) -> 0 | G10: =(E10-F10)^2 -> 6.1747611
B11: =Datos_OWID!B9 -> 4 | C11: =Datos_OWID!E9 -> 50 | D11: =Modelo_SIRD!M11 -> 0 | E11: =LN(C11+1) -> 3.9318256 | F11: =LN(D11+1) -> 0 | G11: =(E11-F11)^2 -> 15.459253
B12: =Datos_OWID!B10 -> 5 | C12: =Datos_OWID!E10 -> 61 | D12: =Modelo_SIRD!M12 -> 0.42 | E12: =LN(C12+1) -> 4.1271344 | F12: =LN(D12+1) -> 0.35065687 | G12: =(E12-F12)^2 -> 14.261782
B13: =Datos_OWID!B11 -> 6 | C13: =Datos_OWID!E11 -> 74 | D13: =Modelo_SIRD!M13 -> 0.96599815 | E13: =LN(C13+1) -> 4.3174881 | F13: =LN(D13+1) -> 0.67600008 | G13: =(E13-F13)^2 -> 13.260435
B14: =Datos_OWID!B12 -> 7 | C14: =Datos_OWID!E12 -> 74 | D14: =Modelo_SIRD!M14 -> 1.8931526 | E14: =LN(C14+1) -> 4.3174881 | F14: =LN(D14+1) -> 1.0623468 | G14: =(E14-F14)^2 -> 10.595945
B15: =Datos_OWID!B13 -> 8 | C15: =Datos_OWID!E13 -> 132 | D15: =Modelo_SIRD!M15 -> 3.7101534 | E15: =LN(C15+1) -> 4.8903491 | F15: =LN(D15+1) -> 1.5497205 | G15: =(E15-F15)^2 -> 11.1598
B16: =Datos_OWID!B14 -> 9 | C16: =Datos_OWID!E14 -> 115 | D16: =Modelo_SIRD!M16 -> 7.2709652 | E16: =LN(C16+1) -> 4.7535902 | F16: =LN(D16+1) -> 2.1127512 | G16: =(E16-F16)^2 -> 6.9740305
B17: =Datos_OWID!B15 -> 10 | C17: =Datos_OWID!E15 -> 120 | D17: =Modelo_SIRD!M17 -> 14.24887 | E17: =LN(C17+1) -> 4.7957905 | F17: =LN(D17+1) -> 2.7245054 | G17: =(E17-F17)^2 -> 4.2902223
B18: =Datos_OWID!B16 -> 11 | C18: =Datos_OWID!E16 -> 144 | D18: =Modelo_SIRD!M18 -> 27.921937 | E18: =LN(C18+1) -> 4.9767337 | F18: =LN(D18+1) -> 3.3646004 | G18: =(E18-F18)^2 -> 2.5989741
B19: =Datos_OWID!B17 -> 12 | C19: =Datos_OWID!E17 -> 219 | D19: =Modelo_SIRD!M19 -> 54.709803 | E19: =LN(C19+1) -> 5.3936275 | F19: =LN(D19+1) -> 4.0201561 | G19: =(E19-F19)^2 -> 1.8864238
... B125: =Datos_OWID!B123 -> 118 | C125: =Datos_OWID!E123 -> 0 | D125: =Modelo_SIRD!M125 -> 13.64329 | E125: =LN(C125+1) -> 0 | F125: =LN(D125+1) -> 2.6839822 | G125: =(E125-F125)^2 -> 7.2037605
B127: CELDA OBJETIVO (SSE) | D127: =SUM(G8:G125) -> 188.88219 | G127: <-- MINIMIZAR ESTA CELDA CON EL SOLVER
B128: RMSE en escala log | D128: =SQRT(Calibracion!$D$127/118) -> 1.2651864
B129: Error relativo en muertes acumuladas | D129: =(Modelo_SIRD!$D$129-Modelo_SIRD!$D$130)/Modelo_SIRD!$D$130 -> -0.13878277
G130: Un ajuste aceptable tiene error relativo dentro de +/-15%.
B132: INSTRUCCIONES PARA EL SOLVER
B134: 1. Activar el complemento: Archivo > Opciones > Complementos > Administrar 'Complementos de Excel'
B135: > Ir... > tildar 'Solver' > Aceptar. (En Mac: Herramientas > Complementos de Excel.)
B137: 2. Datos > Solver. Configurar:
B138: Establecer objetivo: $D$127 (en esta hoja)
B139: Para: Min
B140: Cambiando celdas: Tramos_Beta!$G$6:$G$14
B142: 3. Restricciones (Agregar):
B143: Tramos_Beta!$G$6:$G$14 >= 0.01
B144: Tramos_Beta!$G$6:$G$14 <= 2.00
B146: 4. Metodo de resolucion: GRG Nonlinear
B147: Tildar 'Convertir variables sin restricciones en no negativas'
... B162: Los tramos estan anclados en hitos de politica verificables, no elegidos para mejorar el ajuste. No agregar tramos para bajar el SSE.

Sheet Sensibilidad
B2: ANALISIS DE SENSIBILIDAD
B3: OVE va a pedir esto. Completar corriendo el modelo con cada combinacion y pegando los resultados.
B5: ESCENARIO ACTUAL (lectura automatica)
B6: IFR base | C6: =Parametros!$C$13 -> 0.006
B7: Duracion infecciosa (dias) | C7: =Parametros!$C$12 -> 10
B8: VE contra muerte | C8: =Parametros!$C$15 -> 0.7
B9: Infecciones acumuladas | C9: =Modelo_SIRD!$D$128 -> 19509571
B10: Tasa de ataque | C10: =Modelo_SIRD!$D$128/Parametros!$C$6 -> 0.4286845
B11: Muertes modeladas | C11: =Modelo_SIRD!$D$129 -> 111001.43
B13: GRILLA DE ESCENARIOS
B14: Procedimiento: cambiar los parametros en la hoja Parametros, correr el Solver, y pegar los resultados en esta tabla.
B15: Escenario | C15: IFR | D15: D (dias) | E15: VE | F15: Infecciones acum. | G15: Tasa de ataque | H15: SSE final
B16: Central | C16: 0.006 | D16: 10 | E16: 0.7
B17: IFR bajo | C17: 0.004 | D17: 10 | E17: 0.7
B18: IFR alto | C18: 0.009 | D18: 10 | E18: 0.7
B19: D corto | C19: 0.006 | D19: 7 | E19: 0.7
B20: D largo | C20: 0.006 | D20: 14 | E20: 0.7
B21: VE baja | C21: 0.006 | D21: 10 | E21: 0.6
B22: VE alta | C22: 0.006 | D22: 10 | E22: 0.8
B23: Pesimista (IFR alto + D largo) | C23: 0.009 | D23: 14 | E23: 0.6
B24: Optimista (IFR bajo + D corto) | C24: 0.004 | D24: 7 | E24: 0.8
B26: Las celdas amarillas se completan manualmente tras cada corrida del Solver.
B27: Reportar en el PCR el RANGO de la tasa de ataque, no solo el valor central.

Sheet Fuentes
B2: FUENTES Y REFERENCIAS
B4: DATOS
B5: Our World in Data — COVID-19 | C5: Serie diaria de Argentina agregada a semanal. Descargado de github.com/owid/covid-19-data/blob/master/public/data/owid-covid-data.csv
B6: Poblacion | C6: 45.510.324 (OWID/INDEC 2020)
B8: EFECTIVIDAD VACUNAL
B9: Lancet Regional Health - Americas (2023) | C9: 'The effectiveness of COVID-19 vaccines in Latin America, 2021: a multicenter regional case-control study'. Test-negative, 83.708 adultos hospitalizados en AR/BR/CL/CO, feb-dic 2021. VE contra muerte: BNT162b2 82% (IC 69-90), ChAdOx1 73% (69-77), CoronaVac 65% (60-67), Sputnik V 38% (IC -75 a 78). https://www.sciencedirect.com/science/article/pii/S2667193X23000480
B10: ADVERTENCIA Sputnik V | C10: El IC cruza el cero. Argentina uso Sputnik intensivamente en 2021. Si el mix de dosis del prestamo lo incluye en proporcion significativa, la incertidumbre sobre muertes evitadas es alta y debe reportarse.
B12: MUERTES EVITADAS POR VACUNACION
B13: Open Forum Infectious Diseases 11(10):ofae528 (2024) | C13: 'Estimated Deaths Averted in Adults by COVID-19 Vaccination in Select Latin American and Caribbean Countries'. 17 paises incluida Argentina, ene 2021 - may 2022. Tras ajustar por subregistro estima mas de 1,49 millones de muertes por COVID-19 en esos paises; sin vacunacion proyecta entre 2,10 y 4,11 millones, de modo que la vacunacion evito entre 610.000 y 2,61 millones de muertes. https://academic.oup.com/ofid/article/11/10/ofae528/7754719
B14: ACCION PENDIENTE | C14: Bajar la Tabla 1 del paper (desagrega por pais) y extraer el valor de Argentina. NO prorratear el total regional por poblacion: supondria homogeneidad en cobertura y estructura etaria que no se cumple entre los 17 paises.
B16: SUBREGISTRO Y TASA DE DETECCION
B17: Rahmandad et al. (2020) | C17: 'Behavioral dynamics of COVID-19: estimating under-reporting, multiple waves, and adherence fatigue across 91 nations'. Ratio mediano casos reales/reportados = 8.5, rango intercuartilico 3.2-22 entre percentiles 10 y 90. https://www.medrxiv.org/content/10.1101/2020.06.24.20139451v3.full
B18: Umbral OMS de positividad | C18: La positividad deberia mantenerse por debajo de 5% para considerar que la vigilancia captura adecuadamente la dinamica. En Argentina llego a 66%.
B20: CRONOLOGIA DE INTERVENCIONES
B21: Romo & Ojeda-Galaviz (2021) | C21: 'It Takes More than Two to Tango with COVID-19: Analyzing Argentina's Early Pandemic Response (Jan 2020-April 2020)'. Int J Environ Res Public Health 18(1):73. Figura 10: cronologia de intervenciones no farmacologicas. https://doi.org/10.3390/ijerph18010073
B22: Divergencias adoptadas | C22: Este modelo NO adopta dos supuestos de ese paper (tomados de Borracchi & Giglio 2020): (a) gamma=0.33 (~3 dias de periodo infeccioso), valor de marzo 2020 hoy considerado bajo; (b) S0=0.9*N ('10% con inmunidad natural'), conjetura sin respaldo empirico que la evidencia serologica posterior contradice.
B24: DOCUMENTOS DEL PRESTAMO
B25: Matriz de Resultados (MdR_CNVG.xlsx) | C25: Indicador 2.1: 35 laboratorios incorporados a la Red (meta 10). Indicador 2.3: 1 laboratorio acreditado en calidad (meta 9). Indicador 3.3: 11.517.714 personas vacunadas (meta 2.000.000).
B26: Matriz de Productos (AR_L1326_Outputs_Physical_Progress.xls) | C26: Producto 2.20: 35 laboratorios equipados. Producto 3.40: 22.459.300 dosis recibidas.
B27: Analisis economico ex ante (DLP_EEO1) | C27: SIR con R0=2.2 (contrafactual) y Re=1.12 (tratamiento), poblacion vulnerable de 1M, D=14 dias, retraso de 50 dias. B/C=3.42, VAN=US$60.269.575. Monetiza solo absentismo laboral y capital humano en edad laboral.
